supercluster/__init__.py
supercluster-0.0.2.dist-info/DESCRIPTION.rst
supercluster-0.0.2.dist-info/METADATA
supercluster-0.0.2.dist-info/RECORD
supercluster-0.0.2.dist-info/WHEEL
supercluster-0.0.2.dist-info/entry_points.txt
supercluster-0.0.2.dist-info/metadata.json
supercluster-0.0.2.dist-info/top_level.txt
