Metadata-Version: 2.0
Name: supercluster
Version: 0.0.2
Summary: Supercluster Network is a special kind of Artifical Neural Network that can contain astronomic amount of neurons and learn in a sudden.
Home-page: https://github.com/mertyildiran/Supercluster
Author: Mehmet Mert Yildiran
Author-email: mert.yildiran@bil.omu.edu.tr
License: MIT
Keywords: artifical neural networks
Platform: UNKNOWN
Classifier: Development Status :: 3 - Alpha
Classifier: Intended Audience :: Developers
Classifier: Topic :: Scientific/Engineering :: Artificial Intelligence
Classifier: License :: OSI Approved :: MIT License
Classifier: Programming Language :: Python :: 2.7
